transcribe_allign_textgrid/__init__.py
transcribe_allign_textgrid/__main__.py
transcribe_allign_textgrid/adapter.py
transcribe_allign_textgrid/cli.py
transcribe_allign_textgrid/whisper_schema.py
transcribe_allign_textgrid-0.1.5.dist-info/LICENCE
transcribe_allign_textgrid-0.1.5.dist-info/METADATA
transcribe_allign_textgrid-0.1.5.dist-info/WHEEL
transcribe_allign_textgrid-0.1.5.dist-info/top_level.txt
transcribe_allign_textgrid-0.1.5.dist-info/RECORD
