Metadata-Version: 2.1
Name: transcribe-allign-textgrid
Version: 0.1.5
Summary: Create for-alligned transcription TextGrids from Audio
Author-email: JJWRoeloffs <jelleroeloffs@gmail.com>
Project-URL: Homepage, https://github.com/JJWRoeloffs/transcribe_allign_textgrid
Project-URL: Bug Tracker, https://github.com/JJWRoeloffs/transcribe_allign_textgrid/issues
Keywords: praat,whisper,force-allign,TextGrid
Classifier: Programming Language :: Python :: 3
Classifier: License :: OSI Approved :: GNU Affero General Public License v3
Classifier: Development Status :: 5 - Production/Stable
Classifier: Intended Audience :: Science/Research
Classifier: Operating System :: OS Independent
Requires-Python: <3.12,>=3.8
License-File: LICENCE
Requires-Dist: praatio ~=5.1
Requires-Dist: jsonschema ~=4.1
